vsrc/nextaddr.v
module nextaddr(

    input wire[31:0] pc,
   
    output wire[31:0] next_pc

);
    
    assign next_pc = pc+4;
   
    
endmodule

vsrc/tools.v
//触发器模板
module Reg #(WIDTH = 1, RESET_VAL = 0) (
  input clk,
  input rst,
  input [WIDTH-1:0] din,
  output reg [WIDTH-1:0] dout,
  input wen
);
  always @(posedge clk) begin
    if (rst) dout <= RESET_VAL;
    else if (wen) dout <= din;
  end
endmodule


module RegisterFile #(ADDR_WIDTH = 1, DATA_WIDTH = 1) (
  input clk,

  input wire[ADDR_WIDTH-1:0] raddr1,
  output wire[DATA_WIDTH-1:0] rdata1,

  input wire[ADDR_WIDTH-1:0] raddr2,
  output wire[DATA_WIDTH-1:0] rdata2,

  input [DATA_WIDTH-1:0] wdata,
  input [ADDR_WIDTH-1:0] waddr,
  input we,

  output [DATA_WIDTH-1:0] register_0
);
  reg [DATA_WIDTH-1:0] rf [2**ADDR_WIDTH-1:0];
  always @(posedge clk) begin
    if (we) rf[waddr] <= wdata;
  end
  assign rdata1=(raddr1==5'b0)?32'b0:rf[raddr1];
  assign rdata2=(raddr2==5'b0)?32'b0:rf[raddr2];
  assign register_0=rf[0];
endmodule

vsrc/pc_reg.v
module pc_reg(
    
    input wire clk,
    input wire[31:0] next_pc,
    input wire rest,

    output reg[31:0] pc
);
    
    // always @(posedge clk) begin
    // if (rest) pc <= 0;
    // else pc <= next_pc;
    // end

    Reg #(32,32'h80000000) i0 (clk,rest,next_pc[31:0],pc[31:0],1'b1);


   
    
endmodule

vsrc/ctrl.v
import "DPI-C" function void ebreak(input int register_0);

module ctrl(

    input wire[6:0] op,
    input wire[2:0] funct3,
    input wire[31:0] register_0,

    output wire regwr

);
    assign regwr = (op == 7'b0010011) && (funct3 == 3'b000);

		always @(*) begin
        if(op == 7'b1110011) ebreak(register_0);
    end 

    
endmodule

vsrc/alu.v
module alu(

    input wire[31:0] alu_src1,
    input wire[31:0] alu_src2,

    output wire[31:0] alu_result

);
    
    wire[31:0] add_result;
    wire[31:0] add_a;
    wire[31:0] add_b;
    wire cin;

    assign cin = 0;
    assign add_a = alu_src1;
    assign add_b = {32{cin}} ^ alu_src2;
    assign add_result = add_a + add_b + {32{cin}};

    assign alu_result = add_result;
    
endmodule

vsrc/regfile.v
module regfile (
    
    input wire clk,

    input wire[4:0] raddr1,
    output wire[31:0] rdata1,

    input wire[4:0] raddr2,
    output wire[31:0] rdata2,

    input wire we,
    input wire [4:0] waddr,
    input wire [31:0] wdata,

    output wire[31:0] register_0

);

    // reg[31:0] regfiles[31:0];
    
    // always @(posedge clk) begin
    //     if(we)begin
    //         regfiles[waddr] <= wdata;
    //     end
    // end

    // assign rdata1 = (raddr1 == 5'b0) ? 32'b0 : regfiles[raddr1];
    // assign rdata2 = (raddr2 == 5'b0) ? 32'b0 : regfiles[raddr2];

    RegisterFile #(5,32) r0 (clk,raddr1[4:0],rdata1[31:0],raddr2[4:0],rdata2[31:0],wdata[31:0],waddr[4:0],we,register_0[31:0]);

endmodule

vsrc/decode.v
module decode(
    
    input wire[31:0] inst,

    output wire[6:0] op,
    output wire[4:0] rs1,
    output wire[4:0] rd,
    output wire[2:0] funct3,
    output wire[31:0] imm

);

    assign op = inst[6:0];
    assign rd = inst[11:7];
    assign rs1 = inst[19:15];
    assign funct3 = inst[14:12];
    
    wire[31:0]immI;

    assign immI = {{20{inst[31]}},inst[31:20]};

    assign imm = immI;
    
endmodule

vsrc/cpu_top.v
module cpu_top(
    
    input wire clk,
    input wire rest,
    input wire[31:0] inst,

    output wire[31:0] inst_addr

);
   
    wire[6:0] op;
    wire[4:0] rs1;
    wire[4:0] rd;
    wire[2:0] funct3;
    wire[31:0] imm;

    decode decode(.inst(inst),

                  .funct3(funct3),
                  .op(op),
                  .rs1(rs1),
                  .rd(rd),
                  .imm(imm));

    wire[31:0] busa;
    wire[31:0] busw;
    wire regwr;
    wire[31:0] register_0;

    regfile regfile(.clk(clk),

                    .raddr1(rs1),
                    .rdata1(busa),

                    .raddr2(),
                    .rdata2(),

                    .we(regwr),
                    .waddr(rd),
                    .wdata(busw),
                    .register_0(register_0));

    alu alu(.alu_src1(busa),
            .alu_src2(imm),

            .alu_result(busw));

    ctrl ctrl(.op(op),
              .funct3(funct3),
              .register_0(register_0),
              
              .regwr(regwr));


    wire[31:0] next_pc;
    wire[31:0] pc;

    pc_reg pc_reg(.clk(clk),
                  .rest(rest),
                  .next_pc(next_pc),
                  .pc(pc));
    
    nextaddr nextaddr(.pc(pc),
                      .next_pc(next_pc));

    assign inst_addr = pc;
endmodule

wave.vcd
$version Generated by VerilatedVcd $end
$timescale 1ps $end

 $scope module TOP $end
  $var wire  1 G clk $end
  $var wire 32 I inst [31:0] $end
  $var wire 32 J inst_addr [31:0] $end
  $var wire  1 H rest $end
  $scope module cpu_top $end
   $var wire 32 P busa [31:0] $end
   $var wire 32 Q busw [31:0] $end
   $var wire  1 G clk $end
   $var wire  3 N funct3 [2:0] $end
   $var wire 32 O imm [31:0] $end
   $var wire 32 I inst [31:0] $end
   $var wire 32 J inst_addr [31:0] $end
   $var wire 32 $ next_pc [31:0] $end
   $var wire  7 K op [6:0] $end
   $var wire 32 % pc [31:0] $end
   $var wire  5 M rd [4:0] $end
   $var wire 32 # register_0 [31:0] $end
   $var wire  1 R regwr $end
   $var wire  1 H rest $end
   $var wire  5 L rs1 [4:0] $end
   $scope module alu $end
    $var wire 32 P add_a [31:0] $end
    $var wire 32 O add_b [31:0] $end
    $var wire 32 Q add_result [31:0] $end
    $var wire 32 Q alu_result [31:0] $end
    $var wire 32 P alu_src1 [31:0] $end
    $var wire 32 O alu_src2 [31:0] $end
    $var wire  1 S cin $end
   $upscope $end
   $scope module ctrl $end
    $var wire  3 N funct3 [2:0] $end
    $var wire  7 K op [6:0] $end
    $var wire 32 # register_0 [31:0] $end
    $var wire  1 R regwr $end
   $upscope $end
   $scope module decode $end
    $var wire  3 N funct3 [2:0] $end
    $var wire 32 O imm [31:0] $end
    $var wire 32 O immI [31:0] $end
    $var wire 32 I inst [31:0] $end
    $var wire  7 K op [6:0] $end
    $var wire  5 M rd [4:0] $end
    $var wire  5 L rs1 [4:0] $end
   $upscope $end
   $scope module nextaddr $end
    $var wire 32 $ next_pc [31:0] $end
    $var wire 32 % pc [31:0] $end
   $upscope $end
   $scope module pc_reg $end
    $var wire  1 G clk $end
    $var wire 32 $ next_pc [31:0] $end
    $var wire 32 % pc [31:0] $end
    $var wire  1 H rest $end
    $scope module i0 $end
     $var wire 32 U RESET_VAL [31:0] $end
     $var wire 32 T WIDTH [31:0] $end
     $var wire  1 G clk $end
     $var wire 32 $ din [31:0] $end
     $var wire 32 % dout [31:0] $end
     $var wire  1 H rst $end
     $var wire  1 V wen $end
    $upscope $end
   $upscope $end
   $scope module regfile $end
    $var wire  1 G clk $end
    $var wire  5 L raddr1 [4:0] $end
    $var wire  5 W raddr2 [4:0] $end
    $var wire 32 P rdata1 [31:0] $end
    $var wire 32 & rdata2 [31:0] $end
    $var wire 32 # register_0 [31:0] $end
    $var wire  5 M waddr [4:0] $end
    $var wire 32 Q wdata [31:0] $end
    $var wire  1 R we $end
    $scope module r0 $end
     $var wire 32 X ADDR_WIDTH [31:0] $end
     $var wire 32 T DATA_WIDTH [31:0] $end
     $var wire  1 G clk $end
     $var wire  5 L raddr1 [4:0] $end
     $var wire  5 W raddr2 [4:0] $end
     $var wire 32 P rdata1 [31:0] $end
     $var wire 32 & rdata2 [31:0] $end
     $var wire 32 # register_0 [31:0] $end
     $var wire 32 ' rf[0] [31:0] $end
     $var wire 32 1 rf[10] [31:0] $end
     $var wire 32 2 rf[11] [31:0] $end
     $var wire 32 3 rf[12] [31:0] $end
     $var wire 32 4 rf[13] [31:0] $end
     $var wire 32 5 rf[14] [31:0] $end
     $var wire 32 6 rf[15] [31:0] $end
     $var wire 32 7 rf[16] [31:0] $end
     $var wire 32 8 rf[17] [31:0] $end
     $var wire 32 9 rf[18] [31:0] $end
     $var wire 32 : rf[19] [31:0] $end
     $var wire 32 ( rf[1] [31:0] $end
     $var wire 32 ; rf[20] [31:0] $end
     $var wire 32 < rf[21] [31:0] $end
     $var wire 32 = rf[22] [31:0] $end
     $var wire 32 > rf[23] [31:0] $end
     $var wire 32 ? rf[24] [31:0] $end
     $var wire 32 @ rf[25] [31:0] $end
     $var wire 32 A rf[26] [31:0] $end
     $var wire 32 B rf[27] [31:0] $end
     $var wire 32 C rf[28] [31:0] $end
     $var wire 32 D rf[29] [31:0] $end
     $var wire 32 ) rf[2] [31:0] $end
     $var wire 32 E rf[30] [31:0] $end
     $var wire 32 F rf[31] [31:0] $end
     $var wire 32 * rf[3] [31:0] $end
     $var wire 32 + rf[4] [31:0] $end
     $var wire 32 , rf[5] [31:0] $end
     $var wire 32 - rf[6] [31:0] $end
     $var wire 32 . rf[7] [31:0] $end
     $var wire 32 / rf[8] [31:0] $end
     $var wire 32 0 rf[9] [31:0] $end
     $var wire  5 M waddr [4:0] $end
     $var wire 32 Q wdata [31:0] $end
     $var wire  1 R we $end
    $upscope $end
   $upscope $end
  $upscope $end
 $upscope $end
$enddefinitions $end


#0
b00000000000000000000000000000000 #
b00000000000000000000000000000100 $
b00000000000000000000000000000000 %
b00000000000000000000000000000000 &
b00000000000000000000000000000000 '
b00000000000000000000000000000000 (
b00000000000000000000000000000000 )
b00000000000000000000000000000000 *
b00000000000000000000000000000000 +
b00000000000000000000000000000000 ,
b00000000000000000000000000000000 -
b00000000000000000000000000000000 .
b00000000000000000000000000000000 /
b00000000000000000000000000000000 0
b00000000000000000000000000000000 1
b00000000000000000000000000000000 2
b00000000000000000000000000000000 3
b00000000000000000000000000000000 4
b00000000000000000000000000000000 5
b00000000000000000000000000000000 6
b00000000000000000000000000000000 7
b00000000000000000000000000000000 8
b00000000000000000000000000000000 9
b00000000000000000000000000000000 :
b00000000000000000000000000000000 ;
b00000000000000000000000000000000 <
b00000000000000000000000000000000 =
b00000000000000000000000000000000 >
b00000000000000000000000000000000 ?
b00000000000000000000000000000000 @
b00000000000000000000000000000000 A
b00000000000000000000000000000000 B
b00000000000000000000000000000000 C
b00000000000000000000000000000000 D
b00000000000000000000000000000000 E
b00000000000000000000000000000000 F
1G
1H
b00000000000000000000000000000000 I
b00000000000000000000000000000000 J
b0000000 K
b00000 L
b00000 M
b000 N
b00000000000000000000000000000000 O
b00000000000000000000000000000000 P
b00000000000000000000000000000000 Q
0R
0S
b00000000000000000000000000100000 T
b10000000000000000000000000000000 U
1V
b00000 W
b00000000000000000000000000000101 X
#1
0G
#2
b10000000000000000000000000000100 $
b10000000000000000000000000000000 %
1G
b10000000000000000000000000000000 J
#3
0G
0H
b00000000000000000000000010010011 I
b0010011 K
b00001 M
1R
#4
b10000000000000000000000000001000 $
b10000000000000000000000000000100 %
1G
b10000000000000000000000000000100 J
#5
0G
b00000000000100001000000100010011 I
b00001 L
b00010 M
b00000000000000000000000000000001 O
b00000000000000000000000000000001 Q
#6
b10000000000000000000000000001100 $
b10000000000000000000000000001000 %
b00000000000000000000000000000001 )
1G
b10000000000000000000000000001000 J
#7
0G
b00000000000100010000000110010011 I
b00010 L
b00011 M
b00000000000000000000000000000001 P
b00000000000000000000000000000010 Q
#8
b10000000000000000000000000010000 $
b10000000000000000000000000001100 %
b00000000000000000000000000000010 *
1G
b10000000000000000000000000001100 J
#24
0G
b00000000000100000000000001110011 I
b1110011 K
b00000 L
b00000 M
b00000000000000000000000000000000 P
b00000000000000000000000000000001 Q
0R
